task2/rom.sv
module rom #(
    parameter   ADDRESS_WIDTH = 8,
                DATA_WIDTH = 8
)(
    input logic                     clk,
    input logic [ADDRESS_WIDTH-1:0] addr1,
    input logic [ADDRESS_WIDTH-1:0] addr2,

    output logic [DATA_WIDTH-1:0]   dout1,
    output logic [DATA_WIDTH-1:0]   dout2

);

logic [DATA_WIDTH-1:0] rom_array  [2**ADDRESS_WIDTH];

initial begin
        $display("Loading rom.");
        $readmemh("sinerom.mem", rom_array);
end;

always_ff @(posedge clk)begin

    dout1 <= rom_array [addr1];
    dout2 <= rom_array [addr2];
end


endmodule

task2/counter.sv
module counter #(
    parameter WIDTH = 8
)(
    // interface signals
    input logic clk, // clock
    input logic rst, // reset
    input logic en, //counter enable
    input logic incr,
    output logic [WIDTH-1:0] count // count output
);

always_ff @ (posedge clk or posedge rst)
    if (rst) count <= {WIDTH{1'b0}};
    else     count <= count + {{WIDTH-1{1'b0}}, en};

endmodule

task2/sinegen.sv
module sinegen #(
    parameter   A_WIDTH = 8,
                D_WIDTH = 8
)(
    input logic                 clk,
    input logic                 rst,
    input logic                 en,
    input logic                 v,

    input logic     [D_WIDTH-1:0]            incr,
    output logic    [D_WIDTH-1:0]           dout1,
    output logic    [D_WIDTH-1:0]           dout2,

);


    logic [A_WIDTH-1:0]         address1;


counter addrCounter (
    .clk (clk),
    .rst (rst),
    .en (en),
    .incr (incr),
    .count (address1)
);

rom sineRom (
    .clk (clk),
    .addr1 (address1),
    .addr2(address1 + v),
    .dout1 (dout1),
    .dout2 (dout2)
);

endmodule

task2/sinegen.vcd
$version Generated by VerilatedVcd $end
$date Tue Nov  7 20:14:23 2023 $end
$timescale 1ps $end

 $scope module TOP $end
  $var wire  1 # clk $end
  $var wire  8 ( dout1 [7:0] $end
  $var wire  8 ) dout2 [7:0] $end
  $var wire  1 % en $end
  $var wire  8 ' incr [7:0] $end
  $var wire  1 $ rst $end
  $var wire  1 & v $end
  $scope module sinegen $end
   $var wire 32 - A_WIDTH [31:0] $end
   $var wire 32 - D_WIDTH [31:0] $end
   $var wire  8 * address1 [7:0] $end
   $var wire  1 # clk $end
   $var wire  8 ( dout1 [7:0] $end
   $var wire  8 ) dout2 [7:0] $end
   $var wire  1 % en $end
   $var wire  8 ' incr [7:0] $end
   $var wire  1 $ rst $end
   $var wire  1 & v $end
   $scope module addrCounter $end
    $var wire 32 - WIDTH [31:0] $end
    $var wire  1 # clk $end
    $var wire  8 * count [7:0] $end
    $var wire  1 % en $end
    $var wire  1 + incr $end
    $var wire  1 $ rst $end
   $upscope $end
   $scope module sineRom $end
    $var wire 32 - ADDRESS_WIDTH [31:0] $end
    $var wire 32 - DATA_WIDTH [31:0] $end
    $var wire  8 * addr1 [7:0] $end
    $var wire  8 , addr2 [7:0] $end
    $var wire  1 # clk $end
    $var wire  8 ( dout1 [7:0] $end
    $var wire  8 ) dout2 [7:0] $end
   $upscope $end
  $upscope $end
 $upscope $end
$enddefinitions $end


#0
1#
0$
1%
p&
b00000001 '
b00000000 (
b00000000 )
b00000000 *
1+
b01000000 ,
b00000000000000000000000000001000 -
#1
0#
#2
1#
t&
b01100100 '
b11111110 (
b01111110 )
b00000001 *
0+
b01100101 ,
#3
0#
#4
1#
b11111101 (
b00011010 )
b00000010 *
b01100110 ,
#5
0#
#6
1#
b00011000 )
b00000011 *
b01100111 ,
#7
0#
#8
1#
b00010111 )
b00000100 *
b01101000 ,
#9
0#
#10
1#
b00010101 )
b00000101 *
b01101001 ,
#11
0#
#12
1#
b00010011 )
b00000110 *
b01101010 ,
#13
0#
#14
1#
b11111100 (
b00010010 )
b00000111 *
b01101011 ,
#15
0#
#16
1#
b00010000 )
b00001000 *
b01101100 ,
#17
0#
#18
1#
b11111011 (
b00001110 )
b00001001 *
b01101101 ,
#19
0#
#20
1#
b11111010 (
b00001101 )
b00001010 *
b01101110 ,
#21
0#
#22
1#
b00001100 )
b00001011 *
b01101111 ,
#23
0#
#24
1#
b11111001 (
b00001010 )
b00001100 *
b01110000 ,
#25
0#
#26
1#
b11111000 (
b00001001 )
b00001101 *
b01110001 ,
#27
0#
#28
1#
b11110111 (
b00001000 )
b00001110 *
b01110010 ,
#29
0#
#30
1#
b11110110 (
b00000111 )
b00001111 *
b01110011 ,
#31
0#
#32
1#
b11110101 (
b00000110 )
b00010000 *
b01110100 ,
#33
0#
#34
1#
b11110100 (
b00000101 )
b00010001 *
b01110101 ,
#35
0#
#36
1#
b11110011 (
b00000100 )
b00010010 *
b01110110 ,
#37
0#
#38
1#
b11110001 (
b00000011 )
b00010011 *
b01110111 ,
#39
0#
#40
1#
b11110000 (
b00010100 *
b01111000 ,
#41
0#
#42
1#
b11101111 (
b00000010 )
b00010101 *
b01111001 ,
#43
0#
#44
1#
b11101101 (
b00000001 )
b00010110 *
b01111010 ,
#45
0#
#46
1#
b11101011 (
b00010111 *
b01111011 ,
#47
0#
#48
1#
b11101010 (
b00000000 )
b00011000 *
b01111100 ,
#49
0#
#50
1#
b11101000 (
b00011001 *
b01111101 ,
#51
0#
#52
1#
b11100110 (
b00011010 *
b01111110 ,
#53
0#
#54
1#
b11100101 (
b00011011 *
b01111111 ,
#55
0#
#56
1#
b11100011 (
b00011100 *
b10000000 ,
#57
0#
#58
1#
b11100001 (
b00011101 *
b10000001 ,
#59
0#
#60
1#
b11011111 (
b00011110 *
b10000010 ,
#61
0#
#62
1#
b11011101 (
b00011111 *
b10000011 ,
#63
0#
#64
1#
b11011010 (
b00100000 *
b10000100 ,
#65
0#
#66
1#
b11011000 (
b00100001 *
b10000101 ,
#67
0#
#68
1#
b11010110 (
b00100010 *
b10000110 ,
#69
0#
#70
1#
b11010100 (
b00000001 )
b00100011 *
b10000111 ,
#71
0#
#72
1#
b11010001 (
b00100100 *
b10001000 ,
#73
0#
#74
1#
b11001111 (
b00000010 )
b00100101 *
b10001001 ,
#75
0#
#76
1#
b11001101 (
b00000011 )
b00100110 *
b10001010 ,
#77
0#
#78
1#
b11001010 (
b00100111 *
b10001011 ,
#79
0#
#80
1#
b11001000 (
b00000100 )
b00101000 *
b10001100 ,
#81
0#
#82
1#
b11000101 (
b00000101 )
b00101001 *
b10001101 ,
#83
0#
#84
1#
b11000010 (
b00000110 )
b00101010 *
b10001110 ,
#85
0#
#86
1#
b11000000 (
b00000111 )
b00101011 *
b10001111 ,
#87
0#
#88
1#
b10111101 (
b00001000 )
b00101100 *
b10010000 ,
#89
0#
#90
1#
b10111010 (
b00001001 )
b00101101 *
b10010001 ,
#91
0#
#92
1#
b10111000 (
b00001010 )
b00101110 *
b10010010 ,
#93
0#
#94
1#
b10110101 (
b00001100 )
b00101111 *
b10010011 ,
#95
0#
#96
1#
b10110010 (
b00001101 )
b00110000 *
b10010100 ,
#97
0#
#98
1#
b10101111 (
b00001110 )
b00110001 *
b10010101 ,
#99
0#
#100
1#
b10101100 (
b00010000 )
b00110010 *
b10010110 ,
#101
0#
#102
1#
b10101001 (
b00010010 )
b00110011 *
b10010111 ,
#103
0#
#104
1#
b10100110 (
b00010011 )
b00110100 *
b10011000 ,
#105
0#
#106
1#
b10100011 (
b00010101 )
b00110101 *
b10011001 ,
#107
0#
#108
1#
b10100000 (
b00010111 )
b00110110 *
b10011010 ,
#109
0#
#110
1#
b10011101 (
b00011000 )
b00110111 *
b10011011 ,
#111
0#
#112
1#
b10011010 (
b00011010 )
b00111000 *
b10011100 ,
#113
0#
#114
1#
b10010111 (
b00011100 )
b00111001 *
b10011101 ,
#115
0#
#116
1#
b10010100 (
b00011110 )
b00111010 *
b10011110 ,
#117
0#
#118
1#
b10010001 (
b00100000 )
b00111011 *
b10011111 ,
#119
0#
#120
1#
b10001110 (
b00100011 )
b00111100 *
b10100000 ,
#121
0#
#122
1#
b10001011 (
b00100101 )
b00111101 *
b10100001 ,
#123
0#
#124
1#
b10001000 (
b00100111 )
b00111110 *
b10100010 ,
#125
0#
#126
1#
b10000101 (
b00101001 )
b00111111 *
b10100011 ,
#127
0#
#128
1#
b10000010 (
b00101100 )
b01000000 *
b10100100 ,
#129
0#
#130
1#
b01111110 (
b00101110 )
b01000001 *
b10100101 ,
#131
0#
#132
1#
b01111011 (
b00110000 )
b01000010 *
b10100110 ,
#133
0#
#134
1#
b01111000 (
b00110011 )
b01000011 *
b10100111 ,
#135
0#
#136
1#
b01110101 (
b00110101 )
b01000100 *
b10101000 ,
#137
0#
#138
1#
b01110010 (
b00111000 )
b01000101 *
b10101001 ,
#139
0#
#140
1#
b01101111 (
b00111011 )
b01000110 *
b10101010 ,
#141
0#
#142
1#
b01101100 (
b00111101 )
b01000111 *
b10101011 ,
#143
0#
#144
1#
b01101001 (
b01000000 )
b01001000 *
b10101100 ,
#145
0#
#146
1#
b01100110 (
b01000011 )
b01001001 *
b10101101 ,
#147
0#
#148
1#
b01100011 (
b01000101 )
b01001010 *
b10101110 ,
#149
0#
#150
1#
b01100000 (
b01001000 )
b01001011 *
b10101111 ,
#151
0#
#152
1#
b01011101 (
b01001011 )
b01001100 *
b10110000 ,
#153
0#
#154
1#
b01011010 (
b01001110 )
b01001101 *
b10110001 ,
#155
0#
#156
1#
b01010111 (
b01010001 )
b01001110 *
b10110010 ,
#157
0#
#158
1#
s&
b01100011 '
b01010100 (
b01010100 )
b01001111 *
1+
#159
0#
#160
1#
q&
b01100010 '
b01010001 (
b01010000 *
0+
b10110001 ,
#161
0#
#162
1#
p&
b01100000 '
b01001110 (
b01010001 )
b01010001 *
#163
0#
#164
1#
&
b01011111 '
b01001011 (
b01010010 *
1+
#165
0#
#166
1#
~&
b01011110 '
b01001000 (
b01010011 *
0+
#167
0#
#168
1#
|&
b01011100 '
b01000101 (
b01010100 *
b10110000 ,
#169
0#
#170
1#
b01000011 (
b01001110 )
b01010101 *
b10110001 ,
#171
0#
#172
1#
b01000000 (
b01010001 )
b01010110 *
b10110010 ,
#173
0#
#174
1#
b00111101 (
b01010100 )
b01010111 *
b10110011 ,
#175
0#
#176
1#
b00111011 (
b01010111 )
b01011000 *
b10110100 ,
#177
0#
#178
1#
b00111000 (
b01011010 )
b01011001 *
b10110101 ,
#179
0#
#180
1#
b00110101 (
b01011101 )
b01011010 *
b10110110 ,
#181
0#
#182
1#
b00110011 (
b01100000 )
b01011011 *
b10110111 ,
#183
0#
#184
1#
b00110000 (
b01100011 )
b01011100 *
b10111000 ,
#185
0#
#186
1#
b00101110 (
b01100110 )
b01011101 *
b10111001 ,
#187
0#
#188
1#
b00101100 (
b01101001 )
b01011110 *
b10111010 ,
#189
0#
#190
1#
b00101001 (
b01101100 )
b01011111 *
b10111011 ,
#191
0#
#192
1#
b00100111 (
b01101111 )
b01100000 *
b10111100 ,
#193
0#
#194
1#
b00100101 (
b01110010 )
b01100001 *
b10111101 ,
#195
0#
#196
1#
{&
b01011011 '
b00100011 (
b01110101 )
b01100010 *
1+
#197
0#
#198
1#
y&
b01011010 '
b00100000 (
b01100011 *
0+
b10111100 ,
#199
0#
#200
1#
w&
b01010111 '
b00011110 (
b01110010 )
b01100100 *
1+
b10111011 ,
#201
0#
#202
1#
v&
b01010110 '
b00011100 (
b01101111 )
b01100101 *
0+
#203
0#
#204
1#
u&
b01010101 '
b00011010 (
b01100110 *
1+
#205
0#
#206
1#
b00011000 (
b01100111 *
b10111100 ,
#207
0#
#208
1#
b00010111 (
b01110010 )
b01101000 *
b10111101 ,
#209
0#
#210
1#
b00010101 (
b01110101 )
b01101001 *
b10111110 ,
#211
0#
#212
1#
b00010011 (
b01111000 )
b01101010 *
b10111111 ,
#213
0#
#214
1#
b00010010 (
b01111011 )
b01101011 *
b11000000 ,
#215
0#
#216
1#
b00010000 (
b01111111 )
b01101100 *
b11000001 ,
#217
0#
#218
1#
b00001110 (
b10000010 )
b01101101 *
b11000010 ,
#219
0#
#220
1#
b00001101 (
b10000101 )
b01101110 *
b11000011 ,
#221
0#
#222
1#
s&
b01010100 '
b00001100 (
b10001000 )
b01101111 *
0+
b11000010 ,
#223
0#
#224
1#
&
b01001111 '
b00001010 (
b10000101 )
b01110000 *
1+
b10111111 ,
#225
0#
#226
1#
{&
b01001011 '
b00001001 (
b01111011 )
b01110001 *
b10111100 ,
#227
0#
#228
1#
b00001000 (
b01110010 )
b01110010 *
b10111101 ,
#229
0#
#230
1#
b00000111 (
b01110101 )
b01110011 *
b10111110 ,
#231
0#
#232
1#
b00000110 (
b01111000 )
b01110100 *
b10111111 ,
#233
0#
#234
1#
b00000101 (
b01111011 )
b01110101 *
b11000000 ,
#235
0#
#236
1#
b00000100 (
b01111111 )
b01110110 *
b11000001 ,
#237
0#
#238
1#
b00000011 (
b10000010 )
b01110111 *
b11000010 ,
#239
0#
#240
1#
b10000101 )
b01111000 *
b11000011 ,
#241
0#
#242
1#
b00000010 (
b10001000 )
b01111001 *
b11000100 ,
#243
0#
#244
1#
b00000001 (
b10001011 )
b01111010 *
b11000101 ,
#245
0#
#246
1#
b10001110 )
b01111011 *
b11000110 ,
#247
0#
#248
1#
b00000000 (
b10010001 )
b01111100 *
b11000111 ,
#249
0#
#250
1#
b10010100 )
b01111101 *
b11001000 ,
#251
0#
#252
1#
b10010111 )
b01111110 *
b11001001 ,
#253
0#
#254
1#
b10011010 )
b01111111 *
b11001010 ,
#255
0#
#256
1#
b10011101 )
b10000000 *
b11001011 ,
#257
0#
#258
1#
b10100000 )
b10000001 *
b11001100 ,
#259
0#
#260
1#
b10100011 )
b10000010 *
b11001101 ,
#261
0#
#262
1#
b10100110 )
b10000011 *
b11001110 ,
#263
0#
#264
1#
b10101001 )
b10000100 *
b11001111 ,
#265
0#
#266
1#
b10101100 )
b10000101 *
b11010000 ,
#267
0#
#268
1#
b10101111 )
b10000110 *
b11010001 ,
#269
0#
#270
1#
z&
b01001010 '
b00000001 (
b10110010 )
b10000111 *
0+
#271
0#
#272
1#
y&
b01001001 '
b10001000 *
1+
#273
0#
#274
1#
x&
b01001000 '
b00000010 (
b10001001 *
0+
#275
0#
#276
1#
v&
b01000110 '
b00000011 (
b10001010 *
b11010000 ,
#277
0#
#278
1#
r&
b01000010 '
b10101111 )
b10001011 *
b11001101 ,
#279
0#
#280
1#
q&
b01000001 '
b00000100 (
b10100110 )
b10001100 *
1+
#281
0#
#282
1#
b00000101 (
b10001101 *
b11001110 ,
#283
0#
#284
1#
b00000110 (
b10101001 )
b10001110 *
b11001111 ,
#285
0#
#286
1#
b00000111 (
b10101100 )
b10001111 *
b11010000 ,
#287
0#
#288
1#
b00001000 (
b10101111 )
b10010000 *
b11010001 ,
#289
0#
#290
1#
b00001001 (
b10110010 )
b10010001 *
b11010010 ,
#291
0#
#292
1#
b00001010 (
b10110101 )
b10010010 *
b11010011 ,
#293
0#
#294
1#
b00001100 (
b10111000 )
b10010011 *
b11010100 ,
#295
0#
#296
1#
b00001101 (
b10111010 )
b10010100 *
b11010101 ,
#297
0#
#298
1#
b00001110 (
b10111101 )
b10010101 *
b11010110 ,
#299
0#
#300
1#
b00010000 (
b11000000 )
b10010110 *
b11010111 ,
#301
0#
#302
1#
b00010010 (
b11000010 )
b10010111 *
b11011000 ,
#303
0#
#304
1#
b00010011 (
b11000101 )
b10011000 *
b11011001 ,
#305
0#
#306
1#
b00010101 (
b11001000 )
b10011001 *
b11011010 ,
#307
0#
#308
1#
p&
b01000000 '
b00010111 (
b11001010 )
b10011010 *
0+
#309
0#
#310
1#
?&
b00111111 '
b00011000 (
b10011011 *
1+
#311
0#
#312
1#
<&
b00111100 '
b00011010 (
b10011100 *
0+
b11011000 ,
#313
0#
#314
1#
9&
b00111001 '
b00011100 (
b11000101 )
b10011101 *
1+
b11010110 ,
#315
0#
#316
1#
b00011110 (
b11000000 )
b10011110 *
b11010111 ,
#317
0#
#318
1#
b00100000 (
b11000010 )
b10011111 *
b11011000 ,
#319
0#
#320
1#
b00100011 (
b11000101 )
b10100000 *
b11011001 ,
#321
0#
#322
1#
b00100101 (
b11001000 )
b10100001 *
b11011010 ,
#323
0#
#324
1#
b00100111 (
b11001010 )
b10100010 *
b11011011 ,
#325
0#
#326
1#
b00101001 (
b11001101 )
b10100011 *
b11011100 ,
#327
0#
#328
1#
b00101100 (
b11001111 )
b10100100 *
b11011101 ,
#329
0#
#330
1#
b00101110 (
b11010001 )
b10100101 *
b11011110 ,
#331
0#
#332
1#
b00110000 (
b11010100 )
b10100110 *
b11011111 ,
#333
0#
#334
1#
b00110011 (
b11010110 )
b10100111 *
b11100000 ,
#335
0#
#336
1#
b00110101 (
b11011000 )
b10101000 *
b11100001 ,
#337
0#
#338
1#
b00111000 (
b11011010 )
b10101001 *
b11100010 ,
#339
0#
#340
1#
8&
b00111000 '
b00111011 (
b11011101 )
b10101010 *
0+
#341
0#
#342
1#
5&
b00110101 '
b00111101 (
b10101011 *
1+
b11100000 ,
#343
0#
#344
1#
1&
b00110001 '
b01000000 (
b11011000 )
b10101100 *
b11011101 ,
#345
0#
#346
1#
b01000011 (
b11010001 )
b10101101 *
b11011110 ,
#347
0#
#348
1#
b01000101 (
b11010100 )
b10101110 *
b11011111 ,
#349
0#
#350
1#
b01001000 (
b11010110 )
b10101111 *
b11100000 ,
#351
0#
#352
1#
b01001011 (
b11011000 )
b10110000 *
b11100001 ,
#353
0#
#354
1#
b01001110 (
b11011010 )
b10110001 *
b11100010 ,
#355
0#
#356
1#
b01010001 (
b11011101 )
b10110010 *
b11100011 ,
#357
0#
#358
1#
b01010100 (
b11011111 )
b10110011 *
b11100100 ,
#359
0#
#360
1#
b01010111 (
b11100001 )
b10110100 *
b11100101 ,
#361
0#
#362
1#
b01011010 (
b11100011 )
b10110101 *
b11100110 ,
#363
0#
#364
1#
b01011101 (
b11100101 )
b10110110 *
b11100111 ,
#365
0#
#366
1#
?&
b00101111 '
b01100000 (
b11100110 )
b10110111 *
b11100110 ,
#367
0#
#368
1#
8&
b00101000 '
b01100011 (
b11100101 )
b10111000 *
0+
b11100000 ,
#369
0#
#370
1#
7&
b01100110 (
b11011000 )
b10111001 *
#371
0#
#372
1#
b00100111 '
b01101001 (
b10111010 *
1+
b11100001 ,
#373
0#
#374
1#
b01101100 (
b11011010 )
b10111011 *
b11100010 ,
#375
0#
#376
1#
b01101111 (
b11011101 )
b10111100 *
b11100011 ,
#377
0#
#378
1#
b01110010 (
b11011111 )
b10111101 *
b11100100 ,
#379
0#
#380
1#
b01110101 (
b11100001 )
b10111110 *
b11100101 ,
#381
0#
#382
1#
b01111000 (
b11100011 )
b10111111 *
b11100110 ,
#383
0#
#384
1#
b01111011 (
b11100101 )
b11000000 *
b11100111 ,
#385
0#
#386
1#
b01111111 (
b11100110 )
b11000001 *
b11101000 ,
#387
0#
#388
1#
b10000010 (
b11101000 )
b11000010 *
b11101001 ,
#389
0#
#390
1#
b10000101 (
b11101010 )
b11000011 *
b11101010 ,
#391
0#
#392
1#
6&
b00100110 '
b10001000 (
b11101011 )
b11000100 *
0+
#393
0#
#394
1#
3&
b00100011 '
b10001011 (
b11000101 *
1+
b11101000 ,
#395
0#
#396
1#
?&
b00011111 '
b10001110 (
b11101000 )
b11000110 *
b11100101 ,
#397
0#
#398
1#
b10010001 (
b11100011 )
b11000111 *
b11100110 ,
#399
0#
#400
1#
b10010100 (
b11100101 )
b11001000 *
b11100111 ,
#401
0#
#402
1#
b10010111 (
b11100110 )
b11001001 *
b11101000 ,
#403
0#
#404
1#
b10011010 (
b11101000 )
b11001010 *
b11101001 ,
#405
0#
#406
1#
b10011101 (
b11101010 )
b11001011 *
b11101010 ,
#407
0#
#408
1#
b10100000 (
b11101011 )
b11001100 *
b11101011 ,
#409
0#
#410
1#
b10100011 (
b11101101 )
b11001101 *
b11101100 ,
#411
0#
#412
1#
b10100110 (
b11101111 )
b11001110 *
b11101101 ,
#413
0#
#414
1#
b10101001 (
b11110000 )
b11001111 *
b11101110 ,
#415
0#
#416
1#
b10101100 (
b11110001 )
b11010000 *
b11101111 ,
#417
0#
#418
1#
b10101111 (
b11110011 )
b11010001 *
b11110000 ,
#419
0#
#420
1#
:&
b00011010 '
b10110010 (
b11110100 )
b11010010 *
0+
b11101100 ,
#421
0#
#422
1#
6&
b00010110 '
b10110101 (
b11101111 )
b11010011 *
b11101001 ,
#423
0#
#424
1#
5&
b00010101 '
b10111000 (
b11101010 )
b11010100 *
1+
#425
0#
#426
1#
b10111010 (
b11010101 *
b11101010 ,
#427
0#
#428
1#
b10111101 (
b11101011 )
b11010110 *
b11101011 ,
#429
0#
#430
1#
b11000000 (
b11101101 )
b11010111 *
b11101100 ,
#431
0#
#432
1#
b11000010 (
b11101111 )
b11011000 *
b11101101 ,
#433
0#
#434
1#
b11000101 (
b11110000 )
b11011001 *
b11101110 ,
#435
0#
#436
1#
b11001000 (
b11110001 )
b11011010 *
b11101111 ,
#437
0#
#438
1#
b11001010 (
b11110011 )
b11011011 *
b11110000 ,
#439
0#
#440
1#
4&
b00010100 '
b11001101 (
b11110100 )
b11011100 *
0+
#441
0#
#442
1#
>&
b00001110 '
b11001111 (
b11011101 *
b11101011 ,
#443
0#
#444
1#
<&
b00001100 '
b11010001 (
b11101101 )
b11011110 *
b11101010 ,
#445
0#
#446
1#
b11010100 (
b11101011 )
b11011111 *
b11101011 ,
#447
0#
#448
1#
b11010110 (
b11101101 )
b11100000 *
b11101100 ,
#449
0#
#450
1#
b11011000 (
b11101111 )
b11100001 *
b11101101 ,
#451
0#
#452
1#
b11011010 (
b11110000 )
b11100010 *
b11101110 ,
#453
0#
#454
1#
b11011101 (
b11110001 )
b11100011 *
b11101111 ,
#455
0#
#456
1#
b11011111 (
b11110011 )
b11100100 *
b11110000 ,
#457
0#
#458
1#
b11100001 (
b11110100 )
b11100101 *
b11110001 ,
#459
0#
#460
1#
b11100011 (
b11110101 )
b11100110 *
b11110010 ,
#461
0#
#462
1#
9&
b00001010 '
b11100101 (
b11110110 )
b11100111 *
b11110000 ,
#463
0#
#464
1#
7&
b00000111 '
b11100110 (
b11110100 )
b11101000 *
1+
b11101111 ,
#465
0#
#466
1#
6&
b00000110 '
b11101000 (
b11110011 )
b11101001 *
0+
#467
0#
#468
1#
b11101010 (
b11101010 *
b11110000 ,
#469
0#
#470
1#
b11101011 (
b11110100 )
b11101011 *
b11110001 ,
#471
0#
#472
1#
b11101101 (
b11110101 )
b11101100 *
b11110010 ,
#473
0#
#474
1#
b11101111 (
b11110110 )
b11101101 *
b11110011 ,
#475
0#
#476
1#
b11110000 (
b11110111 )
b11101110 *
b11110100 ,
#477
0#
#478
1#
b11110001 (
b11111000 )
b11101111 *
b11110101 ,
#479
0#
#480
1#
b11110011 (
b11111001 )
b11110000 *
b11110110 ,
#481
0#
#482
1#
b11110100 (
b11111010 )
b11110001 *
b11110111 ,
#483
0#
#484
1#
5&
b00000101 '
b11110101 (
b11110010 *
1+
#485
0#
#486
1#
3&
b00000011 '
b11110110 (
b11110011 *
b11110110 ,
#487
0#
#488
1#
0&
b00000000 '
b11110111 (
b11110100 *
0+
b11110100 ,
#489
0#
#490
1#
b11111000 (
b11111000 )
b11110101 *
b11110101 ,
#491
0#
#492
1#
b11111001 (
b11111001 )
b11110110 *
b11110110 ,
#493
0#
#494
1#
b11111010 (
b11111010 )
b11110111 *
b11110111 ,
#495
0#
#496
1#
b11111000 *
b11111000 ,
#497
0#
#498
1#
b11111011 (
b11111011 )
b11111001 *
b11111001 ,
#499
0#
#500
1#
b11111100 (
b11111100 )
b11111010 *
b11111010 ,
#501
0#
#502
1#
b11111011 *
b11111011 ,
#503
0#
#504
1#
b11111101 (
b11111101 )
b11111100 *
b11111100 ,
#505
0#
#506
1#
b11111101 *
b11111101 ,
#507
0#
#508
1#
b11111110 *
b11111110 ,
#509
0#
#510
1#
b11111111 *
b11111111 ,
#511
0#
#512
1#
b00000000 *
b00000000 ,
#513
0#
#514
1#
b11111110 (
b11111110 )
b00000001 *
b00000001 ,
#515
0#
#516
1#
b11111101 (
b11111101 )
b00000010 *
b00000010 ,
#517
0#
#518
1#
b00000011 *
b00000011 ,
#519
0#
#520
1#
b00000100 *
b00000100 ,
#521
0#
#522
1#
b00000101 *
b00000101 ,
#523
0#
#524
1#
b00000110 *
b00000110 ,
#525
0#
#526
1#
b11111100 (
b11111100 )
b00000111 *
b00000111 ,
#527
0#
#528
1#
b00001000 *
b00001000 ,
#529
0#
#530
1#
b11111011 (
b11111011 )
b00001001 *
b00001001 ,
#531
0#
#532
1#
b11111010 (
b11111010 )
b00001010 *
b00001010 ,
#533
0#
#534
1#
b00001011 *
b00001011 ,
#535
0#
#536
1#
b11111001 (
b11111001 )
b00001100 *
b00001100 ,
#537
0#
#538
1#
b11111000 (
b11111000 )
b00001101 *
b00001101 ,
#539
0#
#540
1#
b11110111 (
b11110111 )
b00001110 *
b00001110 ,
#541
0#
#542
1#
b11110110 (
b11110110 )
b00001111 *
b00001111 ,
#543
0#
#544
1#
b11110101 (
b11110101 )
b00010000 *
b00010000 ,
#545
0#
#546
1#
b11110100 (
b11110100 )
b00010001 *
b00010001 ,
#547
0#
#548
1#
b11110011 (
b11110011 )
b00010010 *
b00010010 ,
#549
0#
#550
1#
b11110001 (
b11110001 )
b00010011 *
b00010011 ,
#551
0#
#552
1#
b11110000 (
b11110000 )
b00010100 *
b00010100 ,
#553
0#
#554
1#
b11101111 (
b11101111 )
b00010101 *
b00010101 ,
#555
0#
#556
1#
b11101101 (
b11101101 )
b00010110 *
b00010110 ,
#557
0#
#558
1#
b11101011 (
b11101011 )
b00010111 *
b00010111 ,
#559
0#
#560
1#
b11101010 (
b11101010 )
b00011000 *
b00011000 ,
#561
0#
#562
1#
b11101000 (
b11101000 )
b00011001 *
b00011001 ,
#563
0#
#564
1#
b11100110 (
b11100110 )
b00011010 *
b00011010 ,
#565
0#
#566
1#
b11100101 (
b11100101 )
b00011011 *
b00011011 ,
#567
0#
#568
1#
b11100011 (
b11100011 )
b00011100 *
b00011100 ,
#569
0#
#570
1#
b11100001 (
b11100001 )
b00011101 *
b00011101 ,
#571
0#
#572
1#
b11011111 (
b11011111 )
b00011110 *
b00011110 ,
#573
0#
#574
1#
b11011101 (
b11011101 )
b00011111 *
b00011111 ,
#575
0#
#576
1#
b11011010 (
b11011010 )
b00100000 *
b00100000 ,
#577
0#
#578
1#
b11011000 (
b11011000 )
b00100001 *
b00100001 ,
#579
0#
#580
1#
b11010110 (
b11010110 )
b00100010 *
b00100010 ,
#581
0#
#582
1#
b11010100 (
b11010100 )
b00100011 *
b00100011 ,
#583
0#
#584
1#
b11010001 (
b11010001 )
b00100100 *
b00100100 ,
#585
0#
#586
1#
b11001111 (
b11001111 )
b00100101 *
b00100101 ,
#587
0#
#588
1#
b11001101 (
b11001101 )
b00100110 *
b00100110 ,
#589
0#
#590
1#
b11001010 (
b11001010 )
b00100111 *
b00100111 ,
#591
0#
#592
1#
b11001000 (
b11001000 )
b00101000 *
b00101000 ,
#593
0#
#594
1#
b11000101 (
b11000101 )
b00101001 *
b00101001 ,
#595
0#
#596
1#
b11000010 (
b11000010 )
b00101010 *
b00101010 ,
#597
0#
#598
1#
b11000000 (
b11000000 )
b00101011 *
b00101011 ,
#599
0#
#600
1#
b10111101 (
b10111101 )
b00101100 *
b00101100 ,
#601
0#
#602
1#
b10111010 (
b10111010 )
b00101101 *
b00101101 ,
#603
0#
#604
1#
b10111000 (
b10111000 )
b00101110 *
b00101110 ,
#605
0#
#606
1#
b10110101 (
b10110101 )
b00101111 *
b00101111 ,
#607
0#
#608
1#
b10110010 (
b10110010 )
b00110000 *
b00110000 ,
#609
0#
#610
1#
b10101111 (
b10101111 )
b00110001 *
b00110001 ,
#611
0#
#612
1#
b10101100 (
b10101100 )
b00110010 *
b00110010 ,
#613
0#
#614
1#
b10101001 (
b10101001 )
b00110011 *
b00110011 ,
#615
0#
#616
1#
b10100110 (
b10100110 )
b00110100 *
b00110100 ,
#617
0#
#618
1#
b10100011 (
b10100011 )
b00110101 *
b00110101 ,
#619
0#
#620
1#
b10100000 (
b10100000 )
b00110110 *
b00110110 ,
#621
0#
#622
1#
b10011101 (
b10011101 )
b00110111 *
b00110111 ,
#623
0#
#624
1#
b10011010 (
b10011010 )
b00111000 *
b00111000 ,
#625
0#
#626
1#
b10010111 (
b10010111 )
b00111001 *
b00111001 ,
#627
0#
#628
1#
b10010100 (
b10010100 )
b00111010 *
b00111010 ,
#629
0#
#630
1#
b10010001 (
b10010001 )
b00111011 *
b00111011 ,
#631
0#
#632
1#
b10001110 (
b10001110 )
b00111100 *
b00111100 ,
#633
0#
#634
1#
b10001011 (
b10001011 )
b00111101 *
b00111101 ,
#635
0#
#636
1#
b10001000 (
b10001000 )
b00111110 *
b00111110 ,
#637
0#
#638
1#
b10000101 (
b10000101 )
b00111111 *
b00111111 ,
#639
0#
#640
1#
b10000010 (
b10000010 )
b01000000 *
b01000000 ,
#641
0#
#642
1#
b01111110 (
b01111110 )
b01000001 *
b01000001 ,
#643
0#
#644
1#
b01111011 (
b01111011 )
b01000010 *
b01000010 ,
#645
0#
#646
1#
b01111000 (
b01111000 )
b01000011 *
b01000011 ,
#647
0#
#648
1#
b01110101 (
b01110101 )
b01000100 *
b01000100 ,
#649
0#
#650
1#
b01110010 (
b01110010 )
b01000101 *
b01000101 ,
#651
0#
#652
1#
b01101111 (
b01101111 )
b01000110 *
b01000110 ,
#653
0#
#654
1#
b01101100 (
b01101100 )
b01000111 *
b01000111 ,
#655
0#
#656
1#
b01101001 (
b01101001 )
b01001000 *
b01001000 ,
#657
0#
#658
1#
b01100110 (
b01100110 )
b01001001 *
b01001001 ,
#659
0#
#660
1#
b01100011 (
b01100011 )
b01001010 *
b01001010 ,
#661
0#
#662
1#
b01100000 (
b01100000 )
b01001011 *
b01001011 ,
#663
0#
